embedded_voting/__init__.py
embedded_voting/aggregation/__init__.py
embedded_voting/aggregation/aggregator.py
embedded_voting/aggregation/aggregator_subclasses.py
embedded_voting/embeddings/__init__.py
embedded_voting/embeddings/embeddings.py
embedded_voting/embeddings/embeddings_correlation.py
embedded_voting/embeddings/embeddings_generator.py
embedded_voting/embeddings/embeddings_generator_fully_polarized.py
embedded_voting/embeddings/embeddings_generator_polarized.py
embedded_voting/embeddings/embeddings_generator_uniform.py
embedded_voting/embeddings_from_ratings/__init__.py
embedded_voting/embeddings_from_ratings/embeddings_from_ratings.py
embedded_voting/embeddings_from_ratings/embeddings_from_ratings_correlation.py
embedded_voting/embeddings_from_ratings/embeddings_from_ratings_covariance.py
embedded_voting/embeddings_from_ratings/embeddings_from_ratings_identity.py
embedded_voting/embeddings_from_ratings/embeddings_from_ratings_random.py
embedded_voting/embeddings_from_ratings/embeddings_from_ratings_self.py
embedded_voting/experiments/__init__.py
embedded_voting/experiments/moving_voter.py
embedded_voting/experiments/online_learning.py
embedded_voting/manipulation/__init__.py
embedded_voting/manipulation/collective_manipulation/__init__.py
embedded_voting/manipulation/collective_manipulation/manipulation_coalition.py
embedded_voting/manipulation/collective_manipulation/manipulation_coalition_ordinal.py
embedded_voting/manipulation/collective_manipulation/manipulation_coalition_ordinal_borda.py
embedded_voting/manipulation/collective_manipulation/manipulation_coalition_ordinal_irv.py
embedded_voting/manipulation/collective_manipulation/manipulation_coalition_ordinal_k_approval.py
embedded_voting/manipulation/individual_manipulation/__init__.py
embedded_voting/manipulation/individual_manipulation/manipulation.py
embedded_voting/manipulation/individual_manipulation/manipulation_ordinal.py
embedded_voting-0.1.6.dist-info/AUTHORS.rst
embedded_voting-0.1.6.dist-info/LICENSE
embedded_voting-0.1.6.dist-info/METADATA
embedded_voting-0.1.6.dist-info/WHEEL
embedded_voting-0.1.6.dist-info/top_level.txt
embedded_voting-0.1.6.dist-info/RECORD
