Metadata-Version: 2.1
Name: embedded-voting
Version: 0.1.6
Summary: This contains the code for the work on embedded voting done during my internship at Nokia
Home-page: https://github.com/TheoDlmz/embedded_voting
Author: Théo Delemazure
Author-email: theo.delemazure@ens.fr
License: GNU General Public License v3
Keywords: embedded_voting
Classifier: Development Status :: 2 - Pre-Alpha
Classifier: Intended Audience :: Developers
Classifier: License :: OSI Approved :: GNU General Public License v3 (GPLv3)
Classifier: Natural Language :: English
Classifier: Programming Language :: Python :: 3
Classifier: Programming Language :: Python :: 3.8
Classifier: Programming Language :: Python :: 3.9
Classifier: Programming Language :: Python :: 3.10
Requires-Python: >=3.8
License-File: LICENSE
License-File: AUTHORS.rst
Requires-Dist: numpy
Requires-Dist: matplotlib
Requires-Dist: python-ternary
Requires-Dist: scikit-learn
Requires-Dist: tqdm
